auto_download/__init__.py
auto_download/wrds_download.py
io_with_database/__init__.py
io_with_database/database_writer.py
io_with_database/wrds_writer.py
woojicap_dataprep-0.0.1.dist-info/METADATA
woojicap_dataprep-0.0.1.dist-info/WHEEL
woojicap_dataprep-0.0.1.dist-info/top_level.txt
woojicap_dataprep-0.0.1.dist-info/RECORD
