Metadata-Version: 2.1
Name: woojicap-dataprep
Version: 0.0.1
Summary: Data preparation for WoojiCap
Home-page: UNKNOWN
License: UNKNOWN
Platform: UNKNOWN
Requires-Python: >=3.6
